[
  {
    "brin": "00AA",
    "name": "Barlaeus Gymnasium",
    "websiteUrl": "https://barlaeus.nl",
    "street": "Weteringschans",
    "houseNumber": "31",
    "postalCode": "1017RV",
    "city": "Amsterdam",
    "lat": 52.3629,
    "lon": 4.8926,
    "levels": [
      "VWO"
    ],
    "concepts": [
      "Gymnasium"
    ],
    "denomination": "Openbaar",
    "source": "sample",
    "examens_2023_2024": {
      "VWO": {
        "kandidaten": 112,
        "geslaagden": 102,
        "slagingspercentage": 91.1,
        "gem_cijfer_lijst": 6.97
      }
    },
    "examens_bron": "DUO geslaagden-gezakten-en-cijfers-2023-2024 – vestiging: Barlaeus Gymnasium"
  },
  {
    "brin": "00AB",
    "name": "Montessori Lyceum Amsterdam",
    "websiteUrl": "https://mla.nl",
    "street": "Pieter de Hoochstraat",
    "houseNumber": "59",
    "postalCode": "1071ED",
    "city": "Amsterdam",
    "lat": 52.3555,
    "lon": 4.8829,
    "levels": [
      "VMBO-T",
      "HAVO",
      "VWO"
    ],
    "concepts": [
      "Montessori"
    ],
    "denomination": "Bijzonder",
    "source": "sample",
    "examens_2023_2024": {
      "HAVO": {
        "kandidaten": 256,
        "geslaagden": 219,
        "slagingspercentage": 85.5,
        "gem_cijfer_lijst": 6.43
      },
      "VMBO_TL": {
        "kandidaten": 55,
        "geslaagden": 48,
        "slagingspercentage": 87.3,
        "gem_cijfer_lijst": 6.43
      },
      "VWO": {
        "kandidaten": 209,
        "geslaagden": 188,
        "slagingspercentage": 90.0,
        "gem_cijfer_lijst": 6.91
      }
    },
    "examens_bron": "DUO geslaagden-gezakten-en-cijfers-2023-2024 – vestiging: Montessori SGM Amsterdam"
  },
  {
    "brin": "00AC",
    "name": "Hyperion Lyceum",
    "websiteUrl": "https://hyperionlyceum.nl",
    "street": "Voorlandpad",
    "houseNumber": "13",
    "postalCode": "1093BJ",
    "city": "Amsterdam",
    "lat": 52.3659,
    "lon": 4.9445,
    "levels": [
      "VWO"
    ],
    "concepts": [
      "Tweetalig",
      "Technasium"
    ],
    "denomination": "Bijzonder",
    "source": "sample",
    "examens_2023_2024": {
      "VWO": {
        "kandidaten": 135,
        "geslaagden": 126,
        "slagingspercentage": 93.3,
        "gem_cijfer_lijst": 6.74
      }
    },
    "examens_bron": "DUO geslaagden-gezakten-en-cijfers-2023-2024 – vestiging: loc, Hyperion Lyceum"
  },
  {
    "brin": "21AF",
    "name": "Vossius Gymnasium",
    "websiteUrl": "https://www.vossius.nl",
    "street": "Messchaertstraat",
    "houseNumber": "1",
    "postalCode": "1077WS",
    "city": "Amsterdam",
    "lat": 52.3491,
    "lon": 4.8694,
    "levels": [
      "VWO"
    ],
    "concepts": [
      "Gymnasium"
    ],
    "denomination": "Openbaar",
    "source": "DUO/allecijfers.nl",
    "examens_2023_2024": {
      "VWO": {
        "kandidaten": 133,
        "geslaagden": 127,
        "slagingspercentage": 95.5,
        "gem_cijfer_lijst": 7.16
      }
    },
    "examens_bron": "DUO geslaagden-gezakten-en-cijfers-2023-2024 – vestiging: Vossius Gymnasium"
  },
  {
    "brin": "01ET",
    "name": "St. Ignatiusgymnasium",
    "websiteUrl": "https://www.ignatiusgymnasium.nl",
    "street": "Jan van Eijckstraat",
    "houseNumber": "47",
    "postalCode": "1077LH",
    "city": "Amsterdam",
    "lat": 52.3504,
    "lon": 4.8763,
    "levels": [
      "VWO"
    ],
    "concepts": [
      "Gymnasium"
    ],
    "denomination": "Bijzonder",
    "source": "DUO/allecijfers.nl",
    "examens_2023_2024": {
      "VWO": {
        "kandidaten": 110,
        "geslaagden": 101,
        "slagingspercentage": 91.8,
        "gem_cijfer_lijst": 6.85
      }
    },
    "examens_bron": "DUO geslaagden-gezakten-en-cijfers-2023-2024 – vestiging: St. Ignatiusgymnasium"
  },
  {
    "brin": "14SE",
    "name": "St. Nicolaaslyceum",
    "websiteUrl": "https://www.nicolaaslyceum.nl",
    "street": "Beethovenplein",
    "houseNumber": "2",
    "postalCode": "1077WM",
    "city": "Amsterdam",
    "lat": 52.3467,
    "lon": 4.8741,
    "levels": [
      "HAVO",
      "VWO"
    ],
    "concepts": [
      "Tweetalig"
    ],
    "denomination": "Bijzonder",
    "source": "DUO/allecijfers.nl",
    "examens_2023_2024": {
      "HAVO": {
        "kandidaten": 86,
        "geslaagden": 79,
        "slagingspercentage": 91.9,
        "gem_cijfer_lijst": 6.56
      },
      "VWO": {
        "kandidaten": 105,
        "geslaagden": 100,
        "slagingspercentage": 95.2,
        "gem_cijfer_lijst": 6.92
      }
    },
    "examens_bron": "DUO geslaagden-gezakten-en-cijfers-2023-2024 – vestiging: St. Nicolaaslyceum"
  },
  {
    "brin": "21BH",
    "name": "Spinoza Lyceum Amsterdam",
    "websiteUrl": "https://spinozalyceum.nl",
    "street": "Peter van Anrooystraat",
    "houseNumber": "8",
    "postalCode": "1077VS",
    "city": "Amsterdam",
    "lat": 52.3479,
    "lon": 4.8687,
    "levels": [
      "VMBO-T",
      "HAVO",
      "VWO"
    ],
    "concepts": [
      "Dalton",
      "Gymnasium"
    ],
    "denomination": "Openbaar",
    "source": "DUO/allecijfers.nl/Wikipedia",
    "examens_2023_2024": {
      "HAVO": {
        "kandidaten": 87,
        "geslaagden": 74,
        "slagingspercentage": 85.1,
        "gem_cijfer_lijst": 6.52
      },
      "VMBO_TL": {
        "kandidaten": 47,
        "geslaagden": 41,
        "slagingspercentage": 87.2,
        "gem_cijfer_lijst": 6.35
      },
      "VWO": {
        "kandidaten": 94,
        "geslaagden": 89,
        "slagingspercentage": 94.7,
        "gem_cijfer_lijst": 6.8
      }
    },
    "examens_bron": "DUO geslaagden-gezakten-en-cijfers-2023-2024 – vestiging: SGM Dalton Spinozalyceum"
  },
  {
    "brin": "14RF",
    "name": "Pieter Nieuwland College",
    "websiteUrl": "https://www.pieternieuwland.nl",
    "street": "Nobelweg",
    "houseNumber": "6",
    "postalCode": "1097AR",
    "city": "Amsterdam",
    "lat": 52.3535,
    "lon": 4.9423,
    "levels": [
      "HAVO",
      "VWO"
    ],
    "concepts": [],
    "denomination": "Bijzonder",
    "source": "DUO/allecijfers.nl",
    "examens_2023_2024": {
      "HAVO": {
        "kandidaten": 56,
        "geslaagden": 52,
        "slagingspercentage": 92.9,
        "gem_cijfer_lijst": 6.68
      },
      "VWO": {
        "kandidaten": 39,
        "geslaagden": 36,
        "slagingspercentage": 92.3,
        "gem_cijfer_lijst": 6.8
      }
    },
    "examens_bron": "DUO geslaagden-gezakten-en-cijfers-2023-2024 – vestiging: ZAAM Oost"
  },
  {
    "brin": "14RF",
    "name": "Cygnus Gymnasium",
    "websiteUrl": "https://www.cygnusgymnasium.nl",
    "street": "Vrolikstraat",
    "houseNumber": "8",
    "postalCode": "1091VG",
    "city": "Amsterdam",
    "lat": 52.3591,
    "lon": 4.9209,
    "levels": [
      "VWO"
    ],
    "concepts": [
      "Gymnasium"
    ],
    "denomination": "Bijzonder",
    "source": "DUO/allecijfers.nl",
    "examens_2023_2024": {
      "VWO": {
        "kandidaten": 102,
        "geslaagden": 98,
        "slagingspercentage": 96.1,
        "gem_cijfer_lijst": 6.98
      }
    },
    "examens_bron": "DUO geslaagden-gezakten-en-cijfers-2023-2024 – vestiging: Cygnus Gymnasium"
  },
  {
    "brin": "14RF",
    "name": "Havo De Hof",
    "websiteUrl": "https://www.zaam.nl/scholen/havo-de-hof",
    "street": "Vrolikstraat",
    "houseNumber": "8",
    "postalCode": "1091VG",
    "city": "Amsterdam",
    "lat": 52.3591,
    "lon": 4.9209,
    "levels": [
      "HAVO"
    ],
    "concepts": [],
    "denomination": "Bijzonder",
    "source": "DUO/scholenopdekaart.nl",
    "examens_2023_2024": {
      "HAVO": {
        "kandidaten": 69,
        "geslaagden": 56,
        "slagingspercentage": 81.2,
        "gem_cijfer_lijst": 6.56
      }
    },
    "examens_bron": "DUO geslaagden-gezakten-en-cijfers-2023-2024 – vestiging: Havo de Hof"
  },
  {
    "brin": "17YS",
    "name": "Berlage Lyceum",
    "websiteUrl": "https://berlage.espritscholen.nl",
    "street": "Pieter Lodewijk Takstraat",
    "houseNumber": "33-34",
    "postalCode": "1073KJ",
    "city": "Amsterdam",
    "lat": 52.3533,
    "lon": 4.9023,
    "levels": [
      "VMBO-B",
      "VMBO-K",
      "VMBO-T",
      "HAVO",
      "VWO"
    ],
    "concepts": [
      "Tweetalig"
    ],
    "denomination": "Bijzonder",
    "source": "DUO/allecijfers.nl",
    "examens_2023_2024": {
      "HAVO": {
        "kandidaten": 190,
        "geslaagden": 127,
        "slagingspercentage": 66.8,
        "gem_cijfer_lijst": 6.58
      },
      "VMBO_TL": {
        "kandidaten": 192,
        "geslaagden": 128,
        "slagingspercentage": 66.7,
        "gem_cijfer_lijst": 6.21
      },
      "VWO": {
        "kandidaten": 140,
        "geslaagden": 111,
        "slagingspercentage": 79.3,
        "gem_cijfer_lijst": 6.49
      },
      "VMBO_BL": {
        "kandidaten": 11,
        "geslaagden": 6,
        "slagingspercentage": 54.5,
        "gem_cijfer_lijst": 5.95
      },
      "VMBO_KL": {
        "kandidaten": 44,
        "geslaagden": 40,
        "slagingspercentage": 90.9,
        "gem_cijfer_lijst": 6.25
      }
    },
    "examens_bron": "DUO geslaagden-gezakten-en-cijfers-2023-2024 – vestiging: Esprit Scholengroep"
  },
  {
    "brin": "21GD",
    "name": "Calandlyceum",
    "websiteUrl": "https://calandlyceum.nl",
    "street": "Pieter Calandlaan",
    "houseNumber": "182",
    "postalCode": "1068NT",
    "city": "Amsterdam",
    "lat": 52.3713,
    "lon": 4.8165,
    "levels": [
      "VMBO-T",
      "HAVO",
      "VWO"
    ],
    "concepts": [
      "Gymnasium",
      "Dalton",
      "Technasium",
      "Topsport"
    ],
    "denomination": "Openbaar",
    "source": "DUO/allecijfers.nl",
    "examens_2023_2024": {
      "HAVO": {
        "kandidaten": 125,
        "geslaagden": 85,
        "slagingspercentage": 68.0,
        "gem_cijfer_lijst": 6.3
      },
      "VMBO_TL": {
        "kandidaten": 139,
        "geslaagden": 97,
        "slagingspercentage": 69.8,
        "gem_cijfer_lijst": 6.13
      },
      "VWO": {
        "kandidaten": 75,
        "geslaagden": 57,
        "slagingspercentage": 76.0,
        "gem_cijfer_lijst": 6.52
      }
    },
    "examens_bron": "DUO geslaagden-gezakten-en-cijfers-2023-2024 – vestiging: Calandlyceum"
  },
  {
    "brin": "21GD",
    "name": "Lumion",
    "websiteUrl": "https://www.lumion.nl",
    "street": "Vlaardingenlaan",
    "houseNumber": "25",
    "postalCode": "1062HM",
    "city": "Amsterdam",
    "lat": 52.3698,
    "lon": 4.8276,
    "levels": [
      "VMBO-T",
      "HAVO",
      "VWO"
    ],
    "concepts": [
      "Gepersonaliseerd leren"
    ],
    "denomination": "Openbaar",
    "source": "DUO/allecijfers.nl",
    "examens_2023_2024": {
      "HAVO": {
        "kandidaten": 136,
        "geslaagden": 102,
        "slagingspercentage": 75.0,
        "gem_cijfer_lijst": 6.53
      },
      "VMBO_TL": {
        "kandidaten": 64,
        "geslaagden": 51,
        "slagingspercentage": 79.7,
        "gem_cijfer_lijst": 6.2
      },
      "VWO": {
        "kandidaten": 37,
        "geslaagden": 28,
        "slagingspercentage": 75.7,
        "gem_cijfer_lijst": 6.52
      }
    },
    "examens_bron": "DUO geslaagden-gezakten-en-cijfers-2023-2024 – vestiging: locatie, Lumion"
  },
  {
    "brin": "02AN",
    "name": "Fons Vitae Lyceum",
    "websiteUrl": "https://www.fonsvitaelyceum.nl",
    "street": "Mr. Treublaan",
    "houseNumber": "1",
    "postalCode": "1097DP",
    "city": "Amsterdam",
    "lat": 52.3576,
    "lon": 4.9334,
    "levels": [
      "HAVO",
      "VWO"
    ],
    "concepts": [],
    "denomination": "Bijzonder",
    "source": "DUO/allecijfers.nl",
    "examens_2023_2024": {
      "HAVO": {
        "kandidaten": 70,
        "geslaagden": 61,
        "slagingspercentage": 87.1,
        "gem_cijfer_lijst": 6.42
      },
      "VWO": {
        "kandidaten": 98,
        "geslaagden": 89,
        "slagingspercentage": 90.8,
        "gem_cijfer_lijst": 6.67
      }
    },
    "examens_bron": "DUO geslaagden-gezakten-en-cijfers-2023-2024 – vestiging: Fons Vitae Lyceum"
  },
  {
    "brin": "02AR",
    "name": "Hervormd Lyceum Zuid (HLZ)",
    "websiteUrl": "https://www.hlz.nl",
    "street": "Churchilllaan",
    "houseNumber": "1",
    "postalCode": "1078BA",
    "city": "Amsterdam",
    "lat": 52.3488,
    "lon": 4.8855,
    "levels": [
      "HAVO",
      "VWO"
    ],
    "concepts": [],
    "denomination": "Bijzonder",
    "source": "DUO/scholenopdekaart.nl",
    "examens_2023_2024": {
      "HAVO": {
        "kandidaten": 62,
        "geslaagden": 49,
        "slagingspercentage": 79.0,
        "gem_cijfer_lijst": 6.44
      },
      "VWO": {
        "kandidaten": 52,
        "geslaagden": 45,
        "slagingspercentage": 86.5,
        "gem_cijfer_lijst": 6.67
      }
    },
    "examens_bron": "DUO geslaagden-gezakten-en-cijfers-2023-2024 – vestiging: Het Hervormd Lyc Zuid"
  },
  {
    "brin": "02AP",
    "name": "Het Amsterdams Lyceum",
    "websiteUrl": "https://www.hetamsterdamslyceum.nl",
    "street": "Valeriusplein",
    "houseNumber": "15",
    "postalCode": "1075BJ",
    "city": "Amsterdam",
    "lat": 52.3575,
    "lon": 4.8659,
    "levels": [
      "VWO"
    ],
    "concepts": [
      "Gymnasium"
    ],
    "denomination": "Bijzonder",
    "source": "DUO/allecijfers.nl",
    "examens_2023_2024": {
      "VWO": {
        "kandidaten": 142,
        "geslaagden": 134,
        "slagingspercentage": 94.4,
        "gem_cijfer_lijst": 6.73
      }
    },
    "examens_bron": "DUO geslaagden-gezakten-en-cijfers-2023-2024 – vestiging: Het Amsterdams Lyceum"
  },
  {
    "brin": "01TC",
    "name": "Hervormd Lyceum West (HLW)",
    "websiteUrl": "https://www.hlw.nl",
    "street": "Hemsterhuisstraat",
    "houseNumber": "79",
    "postalCode": "1065JX",
    "city": "Amsterdam",
    "lat": 52.3726,
    "lon": 4.8304,
    "levels": [
      "VMBO-T",
      "HAVO",
      "VWO"
    ],
    "concepts": [
      "Tweetalig",
      "Gymnasium"
    ],
    "denomination": "Bijzonder",
    "source": "DUO/allecijfers.nl",
    "examens_2023_2024": {
      "HAVO": {
        "kandidaten": 65,
        "geslaagden": 52,
        "slagingspercentage": 80.0,
        "gem_cijfer_lijst": 6.38
      },
      "VMBO_TL": {
        "kandidaten": 70,
        "geslaagden": 60,
        "slagingspercentage": 85.7,
        "gem_cijfer_lijst": 6.33
      },
      "VWO": {
        "kandidaten": 22,
        "geslaagden": 17,
        "slagingspercentage": 77.3,
        "gem_cijfer_lijst": 6.7
      }
    },
    "examens_bron": "DUO geslaagden-gezakten-en-cijfers-2023-2024 – vestiging: Hervormd Lyceum West"
  },
  {
    "brin": "21ET",
    "name": "Gerrit van der Veen College",
    "websiteUrl": "https://www.gerritvanderveen.nl",
    "street": "Gerrit van der Veenstraat",
    "houseNumber": "99",
    "postalCode": "1077DT",
    "city": "Amsterdam",
    "lat": 52.3508,
    "lon": 4.879,
    "levels": [
      "HAVO",
      "VWO"
    ],
    "concepts": [],
    "denomination": "Bijzonder",
    "source": "DUO/allecijfers.nl",
    "examens_2023_2024": {
      "HAVO": {
        "kandidaten": 88,
        "geslaagden": 77,
        "slagingspercentage": 87.5,
        "gem_cijfer_lijst": 6.58
      },
      "VWO": {
        "kandidaten": 58,
        "geslaagden": 46,
        "slagingspercentage": 79.3,
        "gem_cijfer_lijst": 6.64
      }
    },
    "examens_bron": "DUO geslaagden-gezakten-en-cijfers-2023-2024 – vestiging: ZAAM Zuid"
  },
  {
    "brin": "16TS",
    "name": "Geert Groote College Amsterdam",
    "websiteUrl": "https://www.geertgrootecollege.nl",
    "street": "Stadionkade",
    "houseNumber": "56",
    "postalCode": "1076BG",
    "city": "Amsterdam",
    "lat": 52.3416,
    "lon": 4.8629,
    "levels": [
      "HAVO",
      "VWO"
    ],
    "concepts": [
      "Vrije School"
    ],
    "denomination": "Bijzonder",
    "source": "DUO/scholenopdekaart.nl",
    "examens_2023_2024": {
      "HAVO": {
        "kandidaten": 73,
        "geslaagden": 64,
        "slagingspercentage": 87.7,
        "gem_cijfer_lijst": 6.64
      },
      "VMBO_TL": {
        "kandidaten": 62,
        "geslaagden": 58,
        "slagingspercentage": 93.5,
        "gem_cijfer_lijst": 6.77
      },
      "VWO": {
        "kandidaten": 34,
        "geslaagden": 29,
        "slagingspercentage": 85.3,
        "gem_cijfer_lijst": 6.68
      }
    },
    "examens_bron": "DUO geslaagden-gezakten-en-cijfers-2023-2024 – vestiging: Vrije School Noord-Holland"
  },
  {
    "brin": "21BH",
    "name": "Spinoza20first",
    "websiteUrl": "https://spinoza20first.nl",
    "street": "Roelof Hartstraat",
    "houseNumber": "2",
    "postalCode": "1071VH",
    "city": "Amsterdam",
    "lat": 52.3545,
    "lon": 4.8766,
    "levels": [
      "VMBO-T",
      "HAVO",
      "VWO"
    ],
    "concepts": [
      "Dalton"
    ],
    "denomination": "Openbaar",
    "source": "scholenopdekaart.nl",
    "examens_2023_2024": {
      "HAVO": {
        "kandidaten": 38,
        "geslaagden": 26,
        "slagingspercentage": 68.4,
        "gem_cijfer_lijst": 6.13
      },
      "VMBO_TL": {
        "kandidaten": 32,
        "geslaagden": 29,
        "slagingspercentage": 90.6,
        "gem_cijfer_lijst": 6.5
      },
      "VWO": {
        "kandidaten": 21,
        "geslaagden": 11,
        "slagingspercentage": 52.4,
        "gem_cijfer_lijst": 6.83
      }
    },
    "examens_bron": "DUO geslaagden-gezakten-en-cijfers-2023-2024 – vestiging: Spinoza20First"
  },
  {
    "brin": "20TS",
    "name": "Comenius Lyceum Amsterdam",
    "websiteUrl": "https://www.comeniuslyceum.nl",
    "street": "Jan Tooropstraat",
    "houseNumber": "2",
    "postalCode": "1062BW",
    "city": "Amsterdam",
    "lat": 52.3655,
    "lon": 4.8302,
    "levels": [
      "VMBO-T",
      "HAVO",
      "VWO"
    ],
    "concepts": [],
    "denomination": "Bijzonder",
    "source": "DUO/scholenopdekaart.nl",
    "examens_2023_2024": null,
    "examens_bron": "DUO 2023-2024 – niet gevonden in dataset"
  },
  {
    "brin": "17YS",
    "name": "ALASCA",
    "websiteUrl": "https://alasca.nl",
    "street": "Geertje Wielemaplein",
    "houseNumber": "1",
    "postalCode": "1095MM",
    "city": "Amsterdam",
    "lat": 52.3618,
    "lon": 4.9512,
    "levels": [
      "HAVO",
      "VWO"
    ],
    "concepts": [
      "Liberal Arts",
      "IB"
    ],
    "denomination": "Bijzonder",
    "source": "allecijfers.nl/DUO"
  },
  {
    "brin": "17VF",
    "name": "ABC Noorderlicht",
    "websiteUrl": "https://abc-noorderlicht.nl",
    "street": "Rode Kruisstraat",
    "houseNumber": "14",
    "postalCode": "1025KN",
    "city": "Amsterdam",
    "lat": 52.395,
    "lon": 4.9191,
    "levels": [
      "VMBO-B",
      "VMBO-K",
      "VMBO-GL",
      "VMBO-T"
    ],
    "concepts": [],
    "denomination": "Bijzonder",
    "source": "allecijfers.nl/DUO"
  },
  {
    "brin": "14RF",
    "name": "Bindelmeer College",
    "websiteUrl": "https://bindelmeer.nl",
    "street": "Gulden Kruis",
    "houseNumber": "5",
    "postalCode": "1103BB",
    "city": "Amsterdam",
    "lat": 52.313,
    "lon": 4.974,
    "levels": [
      "VMBO-B",
      "VMBO-K",
      "VMBO-GL",
      "VMBO-T"
    ],
    "concepts": [],
    "denomination": "Bijzonder",
    "source": "allecijfers.nl/DUO"
  },
  {
    "brin": "21AS",
    "name": "Bredero",
    "websiteUrl": "https://bredero.espritscholen.nl",
    "street": "Gare du Nord",
    "houseNumber": "5",
    "postalCode": "1022GX",
    "city": "Amsterdam",
    "lat": 52.3948,
    "lon": 4.9082,
    "levels": [
      "VMBO-T",
      "HAVO"
    ],
    "concepts": [],
    "denomination": "Openbaar",
    "source": "allecijfers.nl/DUO"
  },
  {
    "brin": "17HB",
    "name": "Calvijn College Amsterdam",
    "websiteUrl": "https://calvijncollege.nl",
    "street": "Pieter Calandlaan",
    "houseNumber": "3",
    "postalCode": "1065KH",
    "city": "Amsterdam",
    "lat": 52.3645,
    "lon": 4.8148,
    "levels": [
      "VMBO-B",
      "VMBO-K",
      "VMBO-T"
    ],
    "concepts": [],
    "denomination": "Bijzonder",
    "source": "allecijfers.nl/DUO"
  },
  {
    "brin": "24TG",
    "name": "Casparus College",
    "websiteUrl": "https://casparuscollege.nl",
    "street": "Talmastraat",
    "houseNumber": "40",
    "postalCode": "1382WB",
    "city": "Weesp",
    "lat": 52.3084,
    "lon": 5.0431,
    "levels": [
      "VMBO-B",
      "VMBO-K",
      "VMBO-GL"
    ],
    "concepts": [],
    "denomination": "Bijzonder",
    "source": "allecijfers.nl/DUO"
  },
  {
    "brin": "14RL",
    "name": "Cburg College",
    "websiteUrl": "https://cburgcollege.nl",
    "street": "Foekje Dillemastraat",
    "houseNumber": "116",
    "postalCode": "1087GN",
    "city": "Amsterdam",
    "lat": 52.367,
    "lon": 4.958,
    "levels": [
      "VMBO-B",
      "VMBO-K",
      "VMBO-GL"
    ],
    "concepts": [],
    "denomination": "Bijzonder",
    "source": "allecijfers.nl/DUO"
  },
  {
    "brin": "23GF",
    "name": "Cheider (vo)",
    "websiteUrl": "https://cheider.nl",
    "street": "Zeelandstraat",
    "houseNumber": "11",
    "postalCode": "1078GG",
    "city": "Amsterdam",
    "lat": 52.3477,
    "lon": 4.8801,
    "levels": [
      "VMBO-GL",
      "VMBO-T",
      "HAVO",
      "VWO"
    ],
    "concepts": [
      "Joods"
    ],
    "denomination": "Bijzonder",
    "source": "allecijfers.nl/DUO"
  },
  {
    "brin": "14RF",
    "name": "College De Meer",
    "websiteUrl": "https://collegedemeer.nl",
    "street": "Lavoisierstraat",
    "houseNumber": "2",
    "postalCode": "1098XB",
    "city": "Amsterdam",
    "lat": 52.3574,
    "lon": 4.9497,
    "levels": [
      "VMBO-B",
      "VMBO-K",
      "VMBO-T"
    ],
    "concepts": [],
    "denomination": "Bijzonder",
    "source": "allecijfers.nl/DUO"
  },
  {
    "brin": "16PS",
    "name": "College ZUYD",
    "websiteUrl": "https://collegeZUYD.nl",
    "street": "Rustenburgerstraat",
    "houseNumber": "436-440",
    "postalCode": "1073GN",
    "city": "Amsterdam",
    "lat": 52.3521,
    "lon": 4.8986,
    "levels": [
      "VMBO-B",
      "VMBO-K",
      "VMBO-GL",
      "VMBO-T"
    ],
    "concepts": [],
    "denomination": "Bijzonder",
    "source": "allecijfers.nl/DUO"
  },
  {
    "brin": "31GM",
    "name": "Cornelius Haga Lyceum",
    "websiteUrl": "https://hagalyceum.nl",
    "street": "Naritaweg",
    "houseNumber": "30",
    "postalCode": "1043BX",
    "city": "Amsterdam",
    "lat": 52.3889,
    "lon": 4.8392,
    "levels": [
      "VMBO-T",
      "HAVO",
      "VWO"
    ],
    "concepts": [
      "Islamitisch"
    ],
    "denomination": "Bijzonder",
    "source": "allecijfers.nl/DUO"
  },
  {
    "brin": "14VY",
    "name": "CSB",
    "websiteUrl": "https://csb.nl",
    "street": "De Cuserstraat",
    "houseNumber": "3",
    "postalCode": "1081CN",
    "city": "Amsterdam",
    "lat": 52.338,
    "lon": 4.8706,
    "levels": [
      "VMBO-T",
      "HAVO",
      "VWO"
    ],
    "concepts": [
      "Tweetalig"
    ],
    "denomination": "Bijzonder",
    "source": "allecijfers.nl/DUO"
  },
  {
    "brin": "21VF",
    "name": "Damstede Lyceum",
    "websiteUrl": "https://damstede.nl",
    "street": "Rode Kruisstraat",
    "houseNumber": "83",
    "postalCode": "1025KP",
    "city": "Amsterdam",
    "lat": 52.3965,
    "lon": 4.92,
    "levels": [
      "HAVO",
      "VWO"
    ],
    "concepts": [],
    "denomination": "Bijzonder",
    "source": "allecijfers.nl/DUO"
  },
  {
    "brin": "31BL",
    "name": "De Amsterdamse MAVO",
    "websiteUrl": "https://deamsterdamsemavo.nl",
    "street": "Linnaeushof",
    "houseNumber": "48",
    "postalCode": "1098CE",
    "city": "Amsterdam",
    "lat": 52.3588,
    "lon": 4.944,
    "levels": [
      "VMBO-T"
    ],
    "concepts": [
      "Humanistisch"
    ],
    "denomination": "Bijzonder",
    "source": "allecijfers.nl/DUO"
  },
  {
    "brin": "21ET",
    "name": "De Apollo",
    "websiteUrl": "https://deapollo.nl",
    "street": "Oudaen",
    "houseNumber": "6",
    "postalCode": "1082VS",
    "city": "Amsterdam",
    "lat": 52.337,
    "lon": 4.8869,
    "levels": [
      "VMBO-T",
      "HAVO"
    ],
    "concepts": [
      "KOVO"
    ],
    "denomination": "Bijzonder",
    "source": "allecijfers.nl/DUO"
  },
  {
    "brin": "25EF",
    "name": "DENISE",
    "websiteUrl": "https://denise.school",
    "street": "Piet Mondriaanstraat",
    "houseNumber": "140",
    "postalCode": "1061SB",
    "city": "Amsterdam",
    "lat": 52.3733,
    "lon": 4.8372,
    "levels": [
      "VMBO-T",
      "HAVO",
      "VWO"
    ],
    "concepts": [],
    "denomination": "Bijzonder",
    "source": "allecijfers.nl/DUO"
  },
  {
    "brin": "31FG",
    "name": "Fiducie College",
    "websiteUrl": "https://fiduciecollege.nl",
    "street": "Derkinderenstraat",
    "houseNumber": "44",
    "postalCode": "1065TG",
    "city": "Amsterdam",
    "lat": 52.3692,
    "lon": 4.8203,
    "levels": [
      "VMBO-T",
      "HAVO"
    ],
    "concepts": [],
    "denomination": "Overige",
    "source": "allecijfers.nl/DUO"
  },
  {
    "brin": "16PN",
    "name": "Joodse Scholengemeenschap Maimonides",
    "websiteUrl": "https://maimonides.nl",
    "street": "Noordbrabantstraat",
    "houseNumber": "17",
    "postalCode": "1079RK",
    "city": "Amsterdam",
    "lat": 52.3413,
    "lon": 4.8935,
    "levels": [
      "VMBO-GL",
      "VMBO-T",
      "HAVO",
      "VWO"
    ],
    "concepts": [
      "Joods"
    ],
    "denomination": "Bijzonder",
    "source": "allecijfers.nl/DUO"
  },
  {
    "brin": "17VF",
    "name": "Kairos College",
    "websiteUrl": "https://kairoscollege.nl",
    "street": "Meeuwenlaan",
    "houseNumber": "134",
    "postalCode": "1021JL",
    "city": "Amsterdam",
    "lat": 52.3973,
    "lon": 4.9341,
    "levels": [
      "VMBO-T",
      "HAVO",
      "VWO"
    ],
    "concepts": [
      "Vrije School"
    ],
    "denomination": "Bijzonder",
    "source": "allecijfers.nl/DUO"
  },
  {
    "brin": "16PS",
    "name": "Kiem Montessori",
    "websiteUrl": "https://kiemmontessori.nl",
    "street": "Tweede Oosterparkstraat",
    "houseNumber": "33",
    "postalCode": "1092AX",
    "city": "Amsterdam",
    "lat": 52.3596,
    "lon": 4.9274,
    "levels": [
      "VMBO-T",
      "HAVO"
    ],
    "concepts": [
      "Montessori"
    ],
    "denomination": "Bijzonder",
    "source": "allecijfers.nl/DUO"
  },
  {
    "brin": "17YS",
    "name": "Het Cartesius",
    "websiteUrl": "https://hetcartesius.nl",
    "street": "Frederik Hendrikplantsoen",
    "houseNumber": "7-A",
    "postalCode": "1052HA",
    "city": "Amsterdam",
    "lat": 52.3771,
    "lon": 4.868,
    "levels": [
      "HAVO",
      "VWO"
    ],
    "concepts": [],
    "denomination": "Bijzonder",
    "source": "allecijfers.nl/DUO"
  },
  {
    "brin": "30GC",
    "name": "Het 4e Gymnasium",
    "websiteUrl": "https://het4egymnasium.nl",
    "street": "Archangelweg",
    "houseNumber": "4",
    "postalCode": "1032CE",
    "city": "Amsterdam",
    "lat": 52.3964,
    "lon": 4.9237,
    "levels": [
      "VWO"
    ],
    "concepts": [
      "Gymnasium"
    ],
    "denomination": "Bijzonder",
    "source": "allecijfers.nl/DUO"
  },
  {
    "brin": "21ET",
    "name": "Huygens College",
    "websiteUrl": "https://huygenscollegeamsterdam.nl",
    "street": "2e C. Huygensstraat",
    "houseNumber": "31",
    "postalCode": "1054CX",
    "city": "Amsterdam",
    "lat": 52.3762,
    "lon": 4.8682,
    "levels": [
      "VMBO-B",
      "VMBO-K",
      "VMBO-T"
    ],
    "concepts": [],
    "denomination": "Bijzonder",
    "source": "allecijfers.nl/DUO"
  },
  {
    "brin": "21FF",
    "name": "Ir. Lely Lyceum",
    "websiteUrl": "https://lelylyceum.nl",
    "street": "Ravenswaaipad",
    "houseNumber": "3",
    "postalCode": "1106AZ",
    "city": "Amsterdam",
    "lat": 52.3105,
    "lon": 4.9712,
    "levels": [
      "VMBO-T",
      "HAVO",
      "VWO"
    ],
    "concepts": [],
    "denomination": "Openbaar",
    "source": "allecijfers.nl/DUO"
  },
  {
    "brin": "16PS",
    "name": "IVKO",
    "websiteUrl": "https://ivko.nl",
    "street": "Rustenburgerstraat",
    "houseNumber": "15",
    "postalCode": "1072ER",
    "city": "Amsterdam",
    "lat": 52.353,
    "lon": 4.8973,
    "levels": [
      "VMBO-T",
      "HAVO"
    ],
    "concepts": [
      "Kunst"
    ],
    "denomination": "Bijzonder",
    "source": "allecijfers.nl/DUO"
  },
  {
    "brin": "17YS",
    "name": "Marcanti College",
    "websiteUrl": "https://marcanti.espritscholen.nl",
    "street": "Jan van Galenstraat",
    "houseNumber": "31",
    "postalCode": "1056AJ",
    "city": "Amsterdam",
    "lat": 52.3759,
    "lon": 4.8614,
    "levels": [
      "VMBO-B",
      "VMBO-K",
      "VMBO-T",
      "HAVO"
    ],
    "concepts": [],
    "denomination": "Bijzonder",
    "source": "allecijfers.nl/DUO"
  },
  {
    "brin": "02PA",
    "name": "Mediacollege Amsterdam",
    "websiteUrl": "https://ma.nl",
    "street": "Dintelstraat",
    "houseNumber": "15",
    "postalCode": "1078JL",
    "city": "Amsterdam",
    "lat": 52.3462,
    "lon": 4.8838,
    "levels": [
      "VMBO-B",
      "VMBO-K",
      "VMBO-GL"
    ],
    "concepts": [
      "Media",
      "ICT"
    ],
    "denomination": "Bijzonder",
    "source": "allecijfers.nl/DUO"
  },
  {
    "brin": "16PS",
    "name": "Metis Montessori Lyceum",
    "websiteUrl": "https://metismontessori.nl",
    "street": "Mauritskade",
    "houseNumber": "58",
    "postalCode": "1092AD",
    "city": "Amsterdam",
    "lat": 52.3604,
    "lon": 4.9266,
    "levels": [
      "HAVO",
      "VWO"
    ],
    "concepts": [
      "Montessori",
      "KOVO"
    ],
    "denomination": "Bijzonder",
    "source": "allecijfers.nl/DUO"
  },
  {
    "brin": "17VF",
    "name": "Metropolis Lyceum",
    "websiteUrl": "https://metropolislyceum.nl",
    "street": "Hagedoornplein",
    "houseNumber": "1-A",
    "postalCode": "1031BV",
    "city": "Amsterdam",
    "lat": 52.3933,
    "lon": 4.9436,
    "levels": [
      "VMBO-T",
      "HAVO",
      "VWO"
    ],
    "concepts": [
      "Dalton"
    ],
    "denomination": "Openbaar",
    "source": "allecijfers.nl/DUO"
  },
  {
    "brin": "16PS",
    "name": "Montessori Lyceum Amsterdam (MLA)",
    "websiteUrl": "https://mla.nl",
    "street": "Pieter de Hoochstraat",
    "houseNumber": "59",
    "postalCode": "1071ED",
    "city": "Amsterdam",
    "lat": 52.3555,
    "lon": 4.8829,
    "levels": [
      "VMBO-T",
      "HAVO",
      "VWO"
    ],
    "concepts": [
      "Montessori"
    ],
    "denomination": "Bijzonder",
    "source": "allecijfers.nl/DUO"
  },
  {
    "brin": "16PS",
    "name": "Montessori Lyceum Oostpoort",
    "websiteUrl": "https://montessoriooostpoort.nl",
    "street": "Polderweg",
    "houseNumber": "3",
    "postalCode": "1093KN",
    "city": "Amsterdam",
    "lat": 52.3648,
    "lon": 4.9347,
    "levels": [
      "VMBO-B",
      "VMBO-K",
      "VMBO-GL",
      "VMBO-T",
      "HAVO",
      "VWO"
    ],
    "concepts": [
      "Montessori"
    ],
    "denomination": "Bijzonder",
    "source": "allecijfers.nl/DUO"
  },
  {
    "brin": "16PS",
    "name": "Montessori Lyceum Pax",
    "websiteUrl": "https://mla.nl",
    "street": "C. van Eesterenlaan",
    "houseNumber": "50",
    "postalCode": "1112HR",
    "city": "Amsterdam",
    "lat": 52.3515,
    "lon": 4.9094,
    "levels": [
      "VMBO-T",
      "HAVO",
      "VWO"
    ],
    "concepts": [
      "Montessori"
    ],
    "denomination": "Bijzonder",
    "source": "allecijfers.nl/DUO"
  },
  {
    "brin": "28DH",
    "name": "Montessori Lyceum Terra Nova",
    "websiteUrl": "https://terranova.nl",
    "street": "Pampuslaan",
    "houseNumber": "1",
    "postalCode": "1087LA",
    "city": "Amsterdam",
    "lat": 52.3622,
    "lon": 4.9651,
    "levels": [
      "VMBO-T",
      "HAVO",
      "VWO"
    ],
    "concepts": [
      "Montessori"
    ],
    "denomination": "Bijzonder",
    "source": "allecijfers.nl/DUO"
  },
  {
    "brin": "17HB",
    "name": "Mundus College",
    "websiteUrl": "https://munduscollege.nl",
    "street": "Burg. Hogguerstraat",
    "houseNumber": "2",
    "postalCode": "1064BA",
    "city": "Amsterdam",
    "lat": 52.3708,
    "lon": 4.8219,
    "levels": [
      "VMBO-B",
      "VMBO-K",
      "VMBO-T"
    ],
    "concepts": [],
    "denomination": "Bijzonder",
    "source": "allecijfers.nl/DUO"
  },
  {
    "brin": "03AQ",
    "name": "OSB Amsterdam",
    "websiteUrl": "https://osb.nl",
    "street": "Gulden Kruis",
    "houseNumber": "5",
    "postalCode": "1103BB",
    "city": "Amsterdam",
    "lat": 52.3133,
    "lon": 4.9741,
    "levels": [
      "VMBO-B",
      "VMBO-K",
      "VMBO-T",
      "HAVO",
      "VWO"
    ],
    "concepts": [],
    "denomination": "Openbaar",
    "source": "allecijfers.nl/DUO"
  },
  {
    "brin": "17VF",
    "name": "Over-Y College",
    "websiteUrl": "https://overycollege.nl",
    "street": "Floraweg",
    "houseNumber": "170",
    "postalCode": "1032KD",
    "city": "Amsterdam",
    "lat": 52.3938,
    "lon": 4.9368,
    "levels": [
      "VMBO-T",
      "HAVO"
    ],
    "concepts": [],
    "denomination": "Bijzonder",
    "source": "allecijfers.nl/DUO"
  },
  {
    "brin": "14RL",
    "name": "Tobiasschool",
    "websiteUrl": "https://tobiasschool.nl",
    "street": "Rietwijkerstraat",
    "houseNumber": "55",
    "postalCode": "1059VN",
    "city": "Amsterdam",
    "lat": 52.3616,
    "lon": 4.8231,
    "levels": [
      "VMBO-B",
      "VMBO-K",
      "VMBO-GL"
    ],
    "concepts": [
      "Vrije School"
    ],
    "denomination": "Bijzonder",
    "source": "allecijfers.nl/DUO"
  },
  {
    "brin": "25EF",
    "name": "Vonk Amsterdam",
    "websiteUrl": "https://vonk.school",
    "street": "Rode Kruisstraat",
    "houseNumber": "40",
    "postalCode": "1025KR",
    "city": "Amsterdam",
    "lat": 52.3957,
    "lon": 4.9198,
    "levels": [
      "VMBO-B",
      "VMBO-K"
    ],
    "concepts": [],
    "denomination": "Bijzonder",
    "source": "allecijfers.nl/DUO"
  },
  {
    "brin": "17VF",
    "name": "Xplore Agora",
    "websiteUrl": "https://xplore-agora.nl",
    "street": "Elzenhagenpad",
    "houseNumber": "2",
    "postalCode": "1022XA",
    "city": "Amsterdam",
    "lat": 52.3912,
    "lon": 4.9358,
    "levels": [
      "VMBO-T",
      "HAVO",
      "VWO"
    ],
    "concepts": [
      "Agora"
    ],
    "denomination": "Bijzonder",
    "source": "allecijfers.nl/DUO"
  },
  {
    "brin": "28CH",
    "name": "Futuris",
    "websiteUrl": "https://futuris.nl",
    "street": "Pandora",
    "houseNumber": "1",
    "postalCode": "1183JD",
    "city": "Amstelveen",
    "lat": 52.3077,
    "lon": 4.8705,
    "levels": [
      "VMBO-B",
      "VMBO-K",
      "VMBO-GL",
      "VMBO-T"
    ],
    "concepts": [],
    "denomination": "Bijzonder",
    "source": "allecijfers.nl/DUO"
  }
]